{"_type":"export","__export_format":4,"__export_date":"2020-04-18T17:54:15.915Z","__export_source":"insomnia.desktop.app:v7.1.1","resources":[{"_id":"req_c6b30f9ce8f64712b6f4c096a99379af","authentication":{},"body":{"mimeType":"application/json","text":"{\n\t\"email\":\"admin@fastfeet.com\",\n\t\"password\": \"123456\"\n}"},"created":1585594801274,"description":"","headers":[{"id":"pair_55f0ffb718af46608ad089e9fabf57b1","name":"Content-Type","value":"application/json"}],"isPrivate":false,"metaSortKey":-1585595850360,"method":"POST","modified":1585763480936,"name":"Sessions","parameters":[],"parentId":"wrk_ebb02ae51243446d8abd11993cb6c897","settingDisableRenderRequestBody":false,"settingEncodeUrl":true,"settingFollowRedirects":"global","settingRebuildPath":true,"settingSendCookies":true,"settingStoreCookies":true,"url":"{{ base_url  }}/sessions","_type":"request"},{"_id":"wrk_ebb02ae51243446d8abd11993cb6c897","created":1585164358266,"description":"","modified":1585164358266,"name":"FastFeet","parentId":null,"_type":"workspace"},{"_id":"req_c582648e2be342279055d1428673622f","authentication":{},"body":{"mimeType":"application/json","text":"{\n\t\"deliveryman_id\": 8\n}"},"created":1586911308033,"description":"","headers":[{"id":"pair_55f0ffb718af46608ad089e9fabf57b1","name":"Content-Type","value":"application/json"}],"isPrivate":false,"metaSortKey":-1585595850335,"method":"POST","modified":1587064362170,"name":"Deliveryman Sessions","parameters":[],"parentId":"wrk_ebb02ae51243446d8abd11993cb6c897","settingDisableRenderRequestBody":false,"settingEncodeUrl":true,"settingFollowRedirects":"global","settingRebuildPath":true,"settingSendCookies":true,"settingStoreCookies":true,"url":"{{ base_url  }}/deliveryman/sessions","_type":"request"},{"_id":"req_6b02b47a3fb24ddd93762926580895c5","authentication":{},"body":{"mimeType":"multipart/form-data","params":[{"description":"","fileName":"/home/vitor/Imagens/lolcoffee.jpg","id":"pair_4147b5079d6e421a808b24c9a77aa99b","name":"file","type":"file","value":""}]},"created":1585595850310,"description":"","headers":[{"id":"pair_6cbc70c1d1f24f3080749bff26cba9a9","name":"Content-Type","value":"multipart/form-data"}],"isPrivate":false,"metaSortKey":-1585595850310,"method":"POST","modified":1585595980044,"name":"Files","parameters":[],"parentId":"wrk_ebb02ae51243446d8abd11993cb6c897","settingDisableRenderRequestBody":false,"settingEncodeUrl":true,"settingFollowRedirects":"global","settingRebuildPath":true,"settingSendCookies":true,"settingStoreCookies":true,"url":"{{ base_url  }}/files","_type":"request"},{"_id":"req_7bbb176cb5194c1a8bee2dd22c849392","authentication":{"token":"{{ token  }}","type":"bearer"},"body":{},"created":1585763404546,"description":"","headers":[],"isPrivate":false,"metaSortKey":-1585763404546,"method":"GET","modified":1586573536668,"name":"Index","parameters":[],"parentId":"fld_94848b83d10546c0b6059c80187ecfa2","settingDisableRenderRequestBody":false,"settingEncodeUrl":true,"settingFollowRedirects":"global","settingRebuildPath":true,"settingSendCookies":true,"settingStoreCookies":true,"url":"{{ base_url  }}/recipients","_type":"request"},{"_id":"fld_94848b83d10546c0b6059c80187ecfa2","created":1585595146363,"description":"","environment":{},"environmentPropertyOrder":null,"metaSortKey":-1585595146400.5,"modified":1585595502818,"name":"Recipients","parentId":"wrk_ebb02ae51243446d8abd11993cb6c897","_type":"request_group"},{"_id":"req_db7f1b18d5d24aa3a1deb69ee00f8c51","authentication":{"token":"{{ token  }}","type":"bearer"},"body":{"mimeType":"application/json","text":"{\n\t\"name\": \"Vitor Araujo\",\n\t\"rua\": \"São Clemente\",\n\t\"numero\": \"114\",\n\t\"complemento\": \"702 Bloco 1\",\n\t\"estado\": \"RJ\",\n\t\"cidade\": \"Rio de Janeiro\",\n\t\"cep\": \"22260002\"\n}"},"created":1585595161309,"description":"","headers":[{"id":"pair_c3ae01f120d740e1b503540fe098e1a9","name":"Content-Type","value":"application/json"}],"isPrivate":false,"metaSortKey":-1585595161309,"method":"POST","modified":1585595327458,"name":"Create","parameters":[],"parentId":"fld_94848b83d10546c0b6059c80187ecfa2","settingDisableRenderRequestBody":false,"settingEncodeUrl":true,"settingFollowRedirects":"global","settingRebuildPath":true,"settingSendCookies":true,"settingStoreCookies":true,"url":"{{ base_url  }}/recipients","_type":"request"},{"_id":"req_f9997402e9ba47cfa7354d5d3ae7e2cb","authentication":{"token":"{{ token  }}","type":"bearer"},"body":{"mimeType":"application/json","text":"{\n\t\"name\": \"Vitor Araujo\",\n\t\"rua\": \"São Clemente\",\n\t\"numero\": \"114\",\n\t\"complemento\": \"702 Bloco 1\",\n\t\"estado\": \"RJ\",\n\t\"cidade\": \"Rio de Janeiro\",\n\t\"cep\": \"22260002\"\n}"},"created":1585595356080,"description":"","headers":[{"id":"pair_b8748e8f38514e8f8fb2b97e761e004b","name":"Content-Type","value":"application/json"}],"isPrivate":false,"metaSortKey":-1585595161259,"method":"PUT","modified":1585595463008,"name":"Update","parameters":[],"parentId":"fld_94848b83d10546c0b6059c80187ecfa2","settingDisableRenderRequestBody":false,"settingEncodeUrl":true,"settingFollowRedirects":"global","settingRebuildPath":true,"settingSendCookies":true,"settingStoreCookies":true,"url":"{{ base_url  }}/recipients/1","_type":"request"},{"_id":"req_4c9c1557270e44c4b83d1c8cbaecbf66","authentication":{"token":"{{ token  }}","type":"bearer"},"body":{},"created":1585595515994,"description":"","headers":[],"isPrivate":false,"metaSortKey":-1585595515994,"method":"GET","modified":1586802110430,"name":"Index","parameters":[],"parentId":"fld_1c8b6feba0ec4219ad4edffa20da53a9","settingDisableRenderRequestBody":false,"settingEncodeUrl":true,"settingFollowRedirects":"global","settingRebuildPath":true,"settingSendCookies":true,"settingStoreCookies":true,"url":"{{ base_url  }}/deliveryman","_type":"request"},{"_id":"fld_1c8b6feba0ec4219ad4edffa20da53a9","created":1585595484795,"description":"","environment":{},"environmentPropertyOrder":null,"metaSortKey":-1585595146388,"modified":1585595497520,"name":"Deliverymen","parentId":"wrk_ebb02ae51243446d8abd11993cb6c897","_type":"request_group"},{"_id":"req_a9e2e2fc492f409c915d6e18eddd5e5b","authentication":{"token":"{{ token  }}","type":"bearer"},"body":{"mimeType":"application/json","text":"{\n\t\"name\": \"Vitor\",\n\t\"email\": \"vitor@gmail.com\"\n}"},"created":1585595540530,"description":"","headers":[{"id":"pair_55472fcdde904141bd32c66ddc923d05","name":"Content-Type","value":"application/json"}],"isPrivate":false,"metaSortKey":-1585595338651.5,"method":"POST","modified":1586639643698,"name":"Create","parameters":[],"parentId":"fld_1c8b6feba0ec4219ad4edffa20da53a9","settingDisableRenderRequestBody":false,"settingEncodeUrl":true,"settingFollowRedirects":"global","settingRebuildPath":true,"settingSendCookies":true,"settingStoreCookies":true,"url":"{{ base_url  }}/deliveryman","_type":"request"},{"_id":"req_00381c8c5b95466f8c092b4d4f690b70","authentication":{"token":"{{ token  }}","type":"bearer"},"body":{"mimeType":"application/json","text":"{\n\t\"name\": \"Felipe Mattos\",\n\t\"email\": \"mattos907@gmail.com\"\n}"},"created":1585595609672,"description":"","headers":[{"id":"pair_55472fcdde904141bd32c66ddc923d05","name":"Content-Type","value":"application/json"}],"isPrivate":false,"metaSortKey":-1585595249980.25,"method":"PUT","modified":1585595623615,"name":"Update","parameters":[],"parentId":"fld_1c8b6feba0ec4219ad4edffa20da53a9","settingDisableRenderRequestBody":false,"settingEncodeUrl":true,"settingFollowRedirects":"global","settingRebuildPath":true,"settingSendCookies":true,"settingStoreCookies":true,"url":"{{ base_url  }}/deliveryman/1","_type":"request"},{"_id":"req_4cf2c0d91e074aa7b315e8b8fe6cb09a","authentication":{"token":"{{ token  }}","type":"bearer"},"body":{},"created":1585595641021,"description":"","headers":[],"isPrivate":false,"metaSortKey":-1585595205644.625,"method":"DELETE","modified":1585595665118,"name":"Delete","parameters":[],"parentId":"fld_1c8b6feba0ec4219ad4edffa20da53a9","settingDisableRenderRequestBody":false,"settingEncodeUrl":true,"settingFollowRedirects":"global","settingRebuildPath":true,"settingSendCookies":true,"settingStoreCookies":true,"url":"{{ base_url  }}/deliveryman/2","_type":"request"},{"_id":"req_640e388f8a5943b7a7407189ba6efd50","authentication":{"token":"{{ token  }}","type":"bearer"},"body":{},"created":1585596124986,"description":"","headers":[],"isPrivate":false,"metaSortKey":-1585596032456,"method":"GET","modified":1586972779212,"name":"Index","parameters":[],"parentId":"fld_2748bfe94b4d4d3ba3d2922208874a7b","settingDisableRenderRequestBody":false,"settingEncodeUrl":true,"settingFollowRedirects":"global","settingRebuildPath":true,"settingSendCookies":true,"settingStoreCookies":true,"url":"{{ base_url  }}/delivery","_type":"request"},{"_id":"fld_2748bfe94b4d4d3ba3d2922208874a7b","created":1585596018473,"description":"","environment":{},"environmentPropertyOrder":null,"metaSortKey":-1585595146338,"modified":1585596023541,"name":"Deliveries","parentId":"wrk_ebb02ae51243446d8abd11993cb6c897","_type":"request_group"},{"_id":"req_2bdd020ec3404f00a42cd977cef7ed39","authentication":{"token":"{{ token  }}","type":"bearer"},"body":{"mimeType":"application/json","text":"{\n\t\"recipient_id\": 1,\n\t\"deliveryman_id\": 8,\n\t\"product\": \"Biscoito\"\n}"},"created":1585596032405,"description":"","headers":[{"id":"pair_43ebb884a0454c94a6c9bcaeee60d604","name":"Content-Type","value":"application/json"}],"isPrivate":false,"metaSortKey":-1585596032406,"method":"POST","modified":1587059732656,"name":"Create","parameters":[],"parentId":"fld_2748bfe94b4d4d3ba3d2922208874a7b","settingDisableRenderRequestBody":false,"settingEncodeUrl":true,"settingFollowRedirects":"global","settingRebuildPath":true,"settingSendCookies":true,"settingStoreCookies":true,"url":"{{ base_url  }}/delivery","_type":"request"},{"_id":"req_b65862e32009450ebcef810d2d2f3168","authentication":{"token":"{{ token  }}","type":"bearer"},"body":{"mimeType":"application/json","text":"{\n\t\"recipient_id\": 1,\n\t\"deliveryman_id\": 1,\n\t\"product\": \"Livro\"\n}"},"created":1585596178860,"description":"","headers":[{"id":"pair_43ebb884a0454c94a6c9bcaeee60d604","name":"Content-Type","value":"application/json"}],"isPrivate":false,"metaSortKey":-1585595941358,"method":"PUT","modified":1585596199566,"name":"Update","parameters":[],"parentId":"fld_2748bfe94b4d4d3ba3d2922208874a7b","settingDisableRenderRequestBody":false,"settingEncodeUrl":true,"settingFollowRedirects":"global","settingRebuildPath":true,"settingSendCookies":true,"settingStoreCookies":true,"url":"{{ base_url  }}/delivery/1","_type":"request"},{"_id":"req_eeb042f8bcf647bd808570ab18e87294","authentication":{"token":"{{ token  }}","type":"bearer"},"body":{},"created":1585596210187,"description":"","headers":[],"isPrivate":false,"metaSortKey":-1585595895834,"method":"DELETE","modified":1586973141771,"name":"Delete","parameters":[],"parentId":"fld_2748bfe94b4d4d3ba3d2922208874a7b","settingDisableRenderRequestBody":false,"settingEncodeUrl":true,"settingFollowRedirects":"global","settingRebuildPath":true,"settingSendCookies":true,"settingStoreCookies":true,"url":"{{ base_url  }}/delivery/13","_type":"request"},{"_id":"req_209cfb293cba464eae3c3bd936964ed8","authentication":{},"body":{},"created":1585596440998,"description":"","headers":[],"isPrivate":false,"metaSortKey":-1585596342109,"method":"GET","modified":1586977677776,"name":"Index","parameters":[],"parentId":"fld_1e3295eca849469396d56aff5f95b4aa","settingDisableRenderRequestBody":false,"settingEncodeUrl":true,"settingFollowRedirects":"global","settingRebuildPath":true,"settingSendCookies":true,"settingStoreCookies":true,"url":"{{ base_url  }}/deliveryman/8/takeaway","_type":"request"},{"_id":"fld_1e3295eca849469396d56aff5f95b4aa","created":1585596292980,"description":"","environment":{},"environmentPropertyOrder":null,"metaSortKey":-1585595146288,"modified":1585596300415,"name":"TakeAway","parentId":"wrk_ebb02ae51243446d8abd11993cb6c897","_type":"request_group"},{"_id":"req_58e915fc7621474d842cc33f7eec3685","authentication":{},"body":{"mimeType":"application/json","text":"{\n\t\"deliveryman_id\": 8,\n\t\"delivery_id\": 17\n}"},"created":1585596342059,"description":"","headers":[{"id":"pair_b3e33488da1b49659bc8817c1a0f9be6","name":"Content-Type","value":"application/json"}],"isPrivate":false,"metaSortKey":-1585596342059,"method":"POST","modified":1587153761897,"name":"Create","parameters":[],"parentId":"fld_1e3295eca849469396d56aff5f95b4aa","settingDisableRenderRequestBody":false,"settingEncodeUrl":true,"settingFollowRedirects":"global","settingRebuildPath":true,"settingSendCookies":true,"settingStoreCookies":true,"url":"{{ base_url  }}/takeaway","_type":"request"},{"_id":"req_faf04a70ad074d40b355117470af7397","authentication":{},"body":{},"created":1585597007466,"description":"","headers":[],"isPrivate":false,"metaSortKey":-1585596548260,"method":"GET","modified":1587153048292,"name":"Index","parameters":[],"parentId":"fld_d8db32e2da70433189a3319fe075281e","settingDisableRenderRequestBody":false,"settingEncodeUrl":true,"settingFollowRedirects":"global","settingRebuildPath":true,"settingSendCookies":true,"settingStoreCookies":true,"url":"{{ base_url  }}/deliveryman/8/deliveries","_type":"request"},{"_id":"fld_d8db32e2da70433189a3319fe075281e","created":1585596530981,"description":"","environment":{},"environmentPropertyOrder":null,"metaSortKey":-1585595146238,"modified":1585596533744,"name":"Arrival","parentId":"wrk_ebb02ae51243446d8abd11993cb6c897","_type":"request_group"},{"_id":"req_5ed1a3b4d23f40feb151e1be18bac132","authentication":{},"body":{"mimeType":"application/json","text":"{\n\t\"deliveryman_id\": 1,\n\t\"delivery_id\": 1,\n\t\"signature_id\": 1\n}"},"created":1585596548210,"description":"","headers":[{"id":"pair_fb1aa7fd2f86444486eb37e926ecde03","name":"Content-Type","value":"application/json"}],"isPrivate":false,"metaSortKey":-1585596548210,"method":"POST","modified":1587150110893,"name":"Create","parameters":[],"parentId":"fld_d8db32e2da70433189a3319fe075281e","settingDisableRenderRequestBody":false,"settingEncodeUrl":true,"settingFollowRedirects":"global","settingRebuildPath":true,"settingSendCookies":true,"settingStoreCookies":true,"url":"{{ base_url  }}/arrival","_type":"request"},{"_id":"req_8e0e3cfa03654597a36bbf1a46e722f0","authentication":{},"body":{},"created":1585597568190,"description":"","headers":[],"isPrivate":false,"metaSortKey":-1585597211538,"method":"GET","modified":1587101158326,"name":"Index","parameters":[],"parentId":"fld_3de85aa98c7b404dbe70bbced287d1f9","settingDisableRenderRequestBody":false,"settingEncodeUrl":true,"settingFollowRedirects":"global","settingRebuildPath":true,"settingSendCookies":true,"settingStoreCookies":true,"url":"{{ base_url  }}/delivery/14/problems","_type":"request"},{"_id":"fld_3de85aa98c7b404dbe70bbced287d1f9","created":1585597200640,"description":"","environment":{},"environmentPropertyOrder":null,"metaSortKey":-1585595146188,"modified":1585597206773,"name":"DeliveryProblems","parentId":"wrk_ebb02ae51243446d8abd11993cb6c897","_type":"request_group"},{"_id":"req_964e152382fc49cf8ecc304a308898ef","authentication":{},"body":{"mimeType":"application/json","text":"{\n\t\"description\": \"Carai vei deu ruim aqui vei\"\n}"},"created":1585597211488,"description":"","headers":[{"id":"pair_763355f1a3f8410d8e35c86c0a9b5aee","name":"Content-Type","value":"application/json"}],"isPrivate":false,"metaSortKey":-1585597211488,"method":"POST","modified":1586805129282,"name":"Create","parameters":[],"parentId":"fld_3de85aa98c7b404dbe70bbced287d1f9","settingDisableRenderRequestBody":false,"settingEncodeUrl":true,"settingFollowRedirects":"global","settingRebuildPath":true,"settingSendCookies":true,"settingStoreCookies":true,"url":"{{ base_url  }}/delivery/13/problems","_type":"request"},{"_id":"req_e5a3d9d21dda49ee846da8183c9af5ca","authentication":{"token":"{{ token  }}","type":"bearer"},"body":{},"created":1585597778685,"description":"","headers":[],"isPrivate":false,"metaSortKey":-1585597778685,"method":"GET","modified":1585597800813,"name":"Index","parameters":[],"parentId":"fld_e08cfd7177cf4e0aa5c51618ce381652","settingDisableRenderRequestBody":false,"settingEncodeUrl":true,"settingFollowRedirects":"global","settingRebuildPath":true,"settingSendCookies":true,"settingStoreCookies":true,"url":"{{ base_url  }}/delivery/problems","_type":"request"},{"_id":"fld_e08cfd7177cf4e0aa5c51618ce381652","created":1585597766573,"description":"","environment":{},"environmentPropertyOrder":null,"metaSortKey":-1585595146138,"modified":1585597774279,"name":"DistributorProblems","parentId":"wrk_ebb02ae51243446d8abd11993cb6c897","_type":"request_group"},{"_id":"req_8c6aac847ce048c3b9aa5077c4b234b9","authentication":{"token":"{{ token  }}","type":"bearer"},"body":{},"created":1585597819988,"description":"","headers":[],"isPrivate":false,"metaSortKey":-1585597778635,"method":"DELETE","modified":1586802477107,"name":"Delete","parameters":[],"parentId":"fld_e08cfd7177cf4e0aa5c51618ce381652","settingDisableRenderRequestBody":false,"settingEncodeUrl":true,"settingFollowRedirects":"global","settingRebuildPath":true,"settingSendCookies":true,"settingStoreCookies":true,"url":"{{ base_url  }}/problem/1/cancel-delivery","_type":"request"},{"_id":"env_dc4583cc9a1f65c4b726640d5b3309f3e5f3bb38","color":null,"created":1585164358284,"data":{"base_url":"http://localhost:3333","token":"eyJhbGciOiJIUzI1NiIsInR5cCI6IkpXVCJ9.eyJpZCI6MSwiaWF0IjoxNTg2NTcxOTMzLCJleHAiOjE1ODcxNzY3MzN9.dukpN7qLj-o0GxjfN9NdWczUA545QxJW82xZ2V-mbq0"},"dataPropertyOrder":{"&":["base_url","token"]},"isPrivate":false,"metaSortKey":1585164358284,"modified":1586571944536,"name":"Base Environment","parentId":"wrk_ebb02ae51243446d8abd11993cb6c897","_type":"environment"},{"_id":"jar_dc4583cc9a1f65c4b726640d5b3309f3e5f3bb38","cookies":[],"created":1585164358290,"modified":1585164358290,"name":"Default Jar","parentId":"wrk_ebb02ae51243446d8abd11993cb6c897","_type":"cookie_jar"}]}